fido_mds/__init__.py
fido_mds/exceptions.py
fido_mds/helpers.py
fido_mds/metadata_store.py
fido_mds/data/__init__.py
fido_mds/data/apple_webauthn_root_ca.pem
fido_mds/data/google_hardware_attestation_root_ca.json
fido_mds/data/metadata.json
fido_mds/models/__init__.py
fido_mds/models/attestation.py
fido_mds/models/fido_mds.py
fido_mds/models/webauthn.py
fido_mds/tests/__init__.py
fido_mds/tests/conftest.py
fido_mds/tests/data.py
fido_mds/tests/test_mds.py
fido_mds/tests/test_verify.py
fido_mds-2026.1.dist-info/licenses/LICENSE
fido_mds-2026.1.dist-info/METADATA
fido_mds-2026.1.dist-info/WHEEL
fido_mds-2026.1.dist-info/top_level.txt
fido_mds-2026.1.dist-info/RECORD
