Metadata-Version: 2.4
Name: fido-mds
Version: 2026.1
Summary: FIDO Alliance Metadata Service in a package
Author-email: Johan Lundberg <lundberg@sunet.se>
License-Expression: BSD-3-Clause
Project-URL: Homepage, https://github.com/SUNET/python-fido-mds
Project-URL: Repository, https://github.com/SUNET/python-fido-mds
Project-URL: Issues, https://github.com/SUNET/python-fido-mds/issues
Classifier: Programming Language :: Python :: 3
Classifier: Programming Language :: Python :: 3.10
Classifier: Programming Language :: Python :: 3.11
Classifier: Programming Language :: Python :: 3.12
Classifier: Programming Language :: Python :: 3.13
Classifier: Programming Language :: Python :: 3 :: Only
Requires-Python: >=3.10
License-File: LICENSE
Requires-Dist: fido2>=1.0.0
Requires-Dist: pydantic>=2.0
Requires-Dist: cryptography
Requires-Dist: pyOpenSSL
Requires-Dist: asn1crypto
Provides-Extra: dev
Requires-Dist: pytest; extra == "dev"
Requires-Dist: pytest-cov; extra == "dev"
Requires-Dist: ruff; extra == "dev"
Requires-Dist: mypy; extra == "dev"
Dynamic: license-file
